source/div_pipeline.v
module div_pipeline (
    input clk,
    input reset,
    input start,
    input [7:0] dividend,
    input [7:0] divisor,
    output reg valid,            // High for one cycle when result is ready
    output reg [7:0] quotient,   // Cleared after one cycle
    output reg [7:0] remainder,   // Cleared after one cycle
    output reg result_ready // Internal flag for new result
);
    // Pipeline stages (0 for load, 1-8 for bit processing)
    reg [7:0] dividend_pipe [0:8];
    reg [7:0] divisor_pipe  [0:8];
    reg [7:0] quotient_pipe [0:8];
    reg [8:0] remainder_pipe [0:8]; // 9 bits for overflow
    reg valid_pipe [0:8];
    
    integer i;
    reg [8:0] temp; // Temporary calculation value
    

    always @(posedge clk or posedge reset) begin
        if (reset) begin
            // Reset all outputs and pipeline
            valid <= 0;
            quotient <= 0;
            remainder <= 0;
            result_ready <= 0;
            for (i = 0; i <= 8; i = i + 1) begin
                valid_pipe[i]    <= 0;
                quotient_pipe[i] <= 0;
                remainder_pipe[i] <= 0;
                dividend_pipe[i] <= 0;
                divisor_pipe[i]  <= 0;
            end
        end else begin
            // Default outputs (will be overridden if new result)
            valid <= 0;
            quotient <= 0;
            remainder <= 0;
            
            // Set outputs for one cycle when result is ready
            if (result_ready) begin
                valid <= 1;
                quotient <= quotient_pipe[8];
                remainder <= remainder_pipe[8][7:0];
                result_ready <= 0; // Clear the flag after output
            end
            
            // Check if new result is available from pipeline
            if (valid_pipe[8] && !result_ready) begin
                result_ready <= 1; // Flag that we have a new result
            end
            
            // Pipeline propagation
            // Stage 8 gets from stage 7
            valid_pipe[8] <= valid_pipe[7];
            quotient_pipe[8] <= quotient_pipe[7];
            remainder_pipe[8] <= remainder_pipe[7];
            dividend_pipe[8] <= dividend_pipe[7];
            divisor_pipe[8] <= divisor_pipe[7];
            
            // Stage 0: load new operation
            if (start) begin
                dividend_pipe[0] <= dividend;
                divisor_pipe[0]  <= divisor;
                quotient_pipe[0] <= 0;
                remainder_pipe[0] <= 0;
                valid_pipe[0]    <= 1;
            end else begin
                valid_pipe[0] <= 0;
            end
            
            // Stages 1-8: bit processing
            for (i = 1; i <= 8; i = i + 1) begin
                // Operand propagation
                dividend_pipe[i] <= dividend_pipe[i-1];
                divisor_pipe[i]  <= divisor_pipe[i-1];
                
                // Extract bit from dividend and shift into remainder
                temp = (remainder_pipe[i-1] << 1) | dividend_pipe[i-1][7 - (i - 1)];
                
                // Subtract divisor if possible
                if (temp >= divisor_pipe[i-1]) begin
                    remainder_pipe[i] <= temp - divisor_pipe[i-1];
                    quotient_pipe[i] <= quotient_pipe[i-1] | (1 << (7 - (i - 1)));
                end else begin
                    remainder_pipe[i] <= temp;
                    quotient_pipe[i] <= quotient_pipe[i-1];
                end
                
                valid_pipe[i] <= valid_pipe[i-1];
            end
        end
    end
endmodule

source/div_no_pipeline.v
// Restoring division algorithm implementation (non-pipelined)
// Source: https://web.mit.edu/6.111/volume2/www/f2019/handouts/L09.pdf
// Source: http://en.wikipedia.org/wiki/Division_(digital)#Restoring_division
module div_no_pipeline 
(   input clk, start,
    input [WIDTH-1:0] dividend,
    input [WIDTH-1:0] divider,
    output reg [WIDTH-1:0] quotient,
    output reg [WIDTH-1:0] remainder,
    output ready);

    parameter WIDTH = 8;     // Bit width for inputs/outputs
    parameter sign = 0;      // If 1, enables signed division

    reg en_proceso;          // Division in progress flag

    reg [WIDTH-1:0] quotient_temp;  // Accumulator for quotient result
    reg [WIDTH*2-1:0] dividend_copy, divider_copy, diff; // Intermediate registers
    reg negative_output;     // Indicates if result should be negative

    reg [5:0] bit;           // Counter for number of bits processed
    reg del_ready = 1;       // Delayed ready signal for synchronization
    wire ready = (!bit) & ~del_ready; // Indicates division completion
    wire [WIDTH-2:0] zeros = 0;       // Zero padding

    initial bit = 0;
    initial negative_output = 0;
    initial en_proceso = 0;

    // Main control logic
    always @( posedge clk ) begin
        del_ready <= !bit;  // Update delayed ready signal
        if (start && !en_proceso) begin
            // Initialize division
            en_proceso = 1;
            bit = WIDTH;
            quotient = 0;
            remainder = 0;
            quotient_temp = 0;

            // Sign handling and operand preparation
            dividend_copy = (!sign || !dividend[WIDTH-1]) ? {1'b0, zeros, dividend} : {1'b0, zeros, ~dividend + 1'b1};
            divider_copy  = (!sign || !divider[WIDTH-1])  ? {1'b0, divider, zeros}  : {1'b0, ~divider + 1'b1, zeros};
            negative_output = sign && ((divider[WIDTH-1] && !dividend[WIDTH-1]) || (!divider[WIDTH-1] && dividend[WIDTH-1]));
        end
        else if (bit > 0) begin
            // One iteration of restoring division
            diff = dividend_copy - divider_copy;
            quotient_temp = quotient_temp << 1;
            if (!diff[WIDTH*2-1]) begin
                dividend_copy = diff;
                quotient_temp[0] = 1'b1;
            end
            divider_copy = divider_copy >> 1;
            bit = bit - 1;
            if (bit == 0) en_proceso = 0;
        end
    end

    // Final output assignment after division completes
    always @(posedge ready) begin
        quotient  = (!negative_output) ? quotient_temp : ~quotient_temp + 1'b1;
        remainder = (!negative_output) ? dividend_copy[WIDTH-1:0] : ~dividend_copy[WIDTH-1:0] + 1'b1;
    end
endmodule

test/div_pipeline_tb.v
`timescale 1ns / 1ps
`include "div_pipeline.v"
`include "div_no_pipeline.v"

module div_pipeline_tb;
    reg clk;
    reg reset;
    reg start;
    reg [7:0] dividend;
    reg [7:0] divisor;
    wire valid;
    wire [7:0] quotient;
    wire [7:0] remainder;
    wire [7:0] quotient_no_pip;
    wire [7:0] remainder_no_pip;
    wire ready;
    wire ready_no_pip;

    div_no_pipeline  div_no_pipeline_inst (
        .clk(clk),
        .dividend(dividend),
        .divider(divisor),
        .quotient(quotient_no_pip),
        .start(start),
        .remainder(remainder_no_pip),
        .ready(ready_no_pip)
    );

    div_pipeline uut (
        .clk(clk),
        .reset(reset),
        .start(start),
        .dividend(dividend),
        .divisor(divisor),
        .valid(valid),
        .quotient(quotient),
        .remainder(remainder),
        .result_ready(ready)
    );

    // Clock generator
    always #5 clk = ~clk;

    // Test cases: dividend / divisor
    reg [7:0] test_dividends [0:7];
    reg [7:0] test_divisors [0:7];
    integer i;

    task send_operands;
        input [7:0] operand_a;
        input [7:0] operand_b;
        begin
            @(posedge clk);
            divisor = operand_a;
            dividend = operand_b;
            start = 1;
            $display("Time %t: Sending operands A=%d, B=%d", $time, operand_a, operand_b);
            @(posedge clk);
            start = 0;
        end
    endtask

    reg [7:0] test1;
    reg [7:0] test2;

    initial begin
        $dumpfile("div_pipeline_tb.vcd");
        $dumpvars(0, div_pipeline_tb);
        $display("Starting div_pipeline testbench...");
        clk = 0;
        reset = 1;
        start = 0;
        dividend = 1;
        divisor = 1;
        
        // Release reset
        #20 reset = 0;

        // Continuously feed data
        for (i = 1; i < 100; i = i + 1) begin
            test1 = $random;
            test2 = $random;

            if (test1 > test2) begin
                send_operands(test2, test1);
            end else begin
                send_operands(test1, test2);              
            end
            // Wait enough time between operations
        end
        
        // Wait enough cycles to empty the pipeline
        #200;

        $finish;
    end

    // Display results when they are ready
    always @(posedge clk) begin
        if (valid) begin
            $display("Valid output -> Quotient = %0d, Remainder = %0d", quotient, remainder);
        end
    end

endmodule

test/div_pipeline_tb.vcd
$date
	Sun Apr 20 18:16:09 2025
$end
$version
	Icarus Verilog
$end
$timescale
	1ps
$end
$scope module div_pipeline_tb $end
$var wire 1 ! valid $end
$var wire 8 " remainder_no_pip [7:0] $end
$var wire 8 # remainder [7:0] $end
$var wire 1 $ ready_no_pip $end
$var wire 1 % ready $end
$var wire 8 & quotient_no_pip [7:0] $end
$var wire 8 ' quotient [7:0] $end
$var reg 1 ( clk $end
$var reg 8 ) dividend [7:0] $end
$var reg 8 * divisor [7:0] $end
$var reg 1 + reset $end
$var reg 1 , start $end
$var reg 8 - test1 [7:0] $end
$var reg 8 . test2 [7:0] $end
$var integer 32 / i [31:0] $end
$scope module div_no_pipeline_inst $end
$var wire 1 ( clk $end
$var wire 8 0 dividend [7:0] $end
$var wire 8 1 divider [7:0] $end
$var wire 1 $ ready $end
$var wire 1 , start $end
$var wire 7 2 zeros [6:0] $end
$var parameter 32 3 WIDTH $end
$var parameter 32 4 sign $end
$var reg 6 5 bit [5:0] $end
$var reg 1 6 del_ready $end
$var reg 16 7 diff [15:0] $end
$var reg 16 8 dividend_copy [15:0] $end
$var reg 16 9 divider_copy [15:0] $end
$var reg 1 : en_proceso $end
$var reg 1 ; negative_output $end
$var reg 8 < quotient [7:0] $end
$var reg 8 = quotient_temp [7:0] $end
$var reg 8 > remainder [7:0] $end
$upscope $end
$scope module uut $end
$var wire 1 ( clk $end
$var wire 8 ? dividend [7:0] $end
$var wire 8 @ divisor [7:0] $end
$var wire 1 + reset $end
$var wire 1 , start $end
$var reg 8 A quotient [7:0] $end
$var reg 8 B remainder [7:0] $end
$var reg 1 % result_ready $end
$var reg 9 C temp [8:0] $end
$var reg 1 ! valid $end
$var integer 32 D i [31:0] $end
$upscope $end
$scope task enviar_operandos $end
$var reg 8 E operand_a [7:0] $end
$var reg 8 F operand_b [7:0] $end
$upscope $end
$upscope $end
$enddefinitions $end
$comment Show the parameter values. $end
$dumpall
b0 4
b1000 3
$end
#0
$dumpvars
bx F
bx E
b1001 D
bx C
b0 B
b0 A
b1 @
b1 ?
bx >
bx =
bx <
0;
0:
bx 9
bx 8
bx 7
16
b0 5
b0 2
b1 1
b1 0
bx /
bx .
bx -
0,
1+
b1 *
b1 )
0(
b0 '
bx &
0%
0$
b0 #
bx "
0!
$end
#5000
b1001 D
1(
#10000
0(
#15000
b1001 D
1(
#20000
0(
b10000001 F
b100100 E
b10000001 .
b100100 -
b1 /
0+
#25000
b1001000000000 9
b10000001 8
b0 =
b0 "
b0 >
b0 &
b0 <
b1000 5
1:
1,
b10000001 )
b10000001 0
b10000001 ?
b100100 *
b100100 1
b100100 @
b0 C
b1001 D
1(
#30000
0(
#35000
06
b1100011 F
b1001 E
b1100011 .
b1001 -
b10 /
0,
b111 5
b100100000000 9
b1110111010000001 7
b1001 D
1(
#40000
0(
#45000
b110 5
b10010000000 9
b1111011110000001 7
1,
b1100011 )
b1100011 0
b1100011 ?
b1001 *
b1001 1
b1001 @
b0 C
b1001 D
1(
#50000
0(
#55000
b10001101 F
b1101 E
b10001101 .
b1101 -
b11 /
0,
b101 5
b1001000000 9
b1111110000000001 7
b0 C
b1001 D
1(
#60000
0(
#65000
b100 5
b100100000 9
b1111111001000001 7
1,
b10001101 )
b10001101 0
b10001101 ?
b1101 *
b1101 1
b1101 @
b0 C
b1001 D
1(
#70000
0(
#75000
b1100101 F
b10010 E
b10010 .
b1100101 -
b100 /
0,
b11 5
b10010000 9
b1111111101100001 7
b0 C
b1001 D
1(
#80000
0(
#85000
b10 5
b1001000 9
b1111111111110001 7
1,
b1100101 )
b1100101 0
b1100101 ?
b10010 *
b10010 1
b10010 @
b0 C
b1001 D
1(
#90000
0(
#95000
b1101 F
b1 E
b1101 .
b1 -
b101 /
0,
b1 5
b100100 9
b1 =
b111001 8
b111001 7
b0 C
b1001 D
1(
#100000
0(
#105000
b10101 "
b10101 >
b11 &
b11 <
1$
0:
b0 5
b10010 9
b10101 8
b11 =
b10101 7
1,
b1101 )
b1101 0
b1101 ?
b1 *
b1 1
b1 @
b0 C
b1001 D
1(
#110000
0(
#115000
16
0$
b1110110 F
b111101 E
b111101 .
b1110110 -
b110 /
0,
b10000000 9
b1101 8
b0 =
b0 "
b0 >
b0 &
b0 <
b1000 5
1:
b111001 C
b1001 D
1(
#120000
0(
#125000
06
1%
b111 5
b1000000 9
b1111111110001101 7
1,
b1110110 )
b1110110 0
b1110110 ?
b111101 *
b111101 1
b111101 @
b111001 C
b1001 D
1(
#130000
0(
#135000
0%
b10101 #
b10101 B
b11 '
b11 A
1!
b11101101 F
b10001100 E
b10001100 .
b11101101 -
b111 /
0,
b110 5
b100000 9
b1111111111001101 7
b1001 C
b1001 D
1(
#140000
0(
#145000
1%
b0 #
b0 B
b0 '
b0 A
0!
b101 5
b10000 9
b1111111111101101 7
1,
b11101101 )
b11101101 0
b11101101 ?
b10001100 *
b10001100 1
b10001100 @
b1001 C
b1001 D
1(
#150000
0(
#155000
0%
b1011 '
b1011 A
1!
b11111001 F
b11000110 E
b11000110 .
b11111001 -
b1000 /
0,
b100 5
b1000 9
b1111111111111101 7
b1011 C
b1001 D
1(
#160000
0(
#165000
1%
b0 '
b0 A
0!
b11 5
b100 9
b1 =
b101 8
b101 7
1,
b11111001 )
b11111001 0
b11111001 ?
b11000110 *
b11000110 1
b11000110 @
b1011 C
b1001 D
1(
#170000
0(
#175000
0%
b1011 #
b1011 B
b1010 '
b1010 A
1!
b11000101 F
b10101010 E
b10101010 .
b11000101 -
b1001 /
0,
b10 5
b10 9
b1 8
b11 =
b1 7
b11101 C
b1001 D
1(
#180000
0(
#185000
1%
b0 #
b0 B
b0 '
b0 A
0!
b1 5
b1 9
b110 =
b1111111111111111 7
1,
b11000101 )
b11000101 0
b11000101 ?
b10101010 *
b10101010 1
b10101010 @
b11101 C
b1001 D
1(
#190000
0(
#195000
0%
b1011 #
b1011 B
b101 '
b101 A
1!
b1101 &
b1101 <
1$
b11100101 F
b1110111 E
b1110111 .
b11100101 -
b1010 /
0,
0:
b0 5
b0 9
b0 8
b1101 =
b0 7
b1 C
b1001 D
1(
#200000
0(
#205000
16
1%
b0 #
b0 B
b0 '
b0 A
0!
0$
b11101110000000 9
b11100101 8
b0 =
b0 &
b0 <
b1000 5
1:
1,
b11100101 )
b11100101 0
b11100101 ?
b1110111 *
b1110111 1
b1110111 @
b1 C
b1001 D
1(
#210000
0(
#215000
06
0%
b1101 '
b1101 A
1!
b10001111 F
b10010 E
b10001111 .
b10010 -
b1011 /
0,
b111 5
b1110111000000 9
b1100010101100101 7
b1110110 C
b1001 D
1(
#220000
0(
#225000
1%
b0 '
b0 A
0!
b110 5
b111011100000 9
b1110001100100101 7
1,
b10001111 )
b10001111 0
b10001111 ?
b10010 *
b10010 1
b10010 @
b1110110 C
b1001 D
1(
#230000
0(
#235000
0%
b111001 #
b111001 B
b1 '
b1 A
1!
b11110010 F
b11001110 E
b11001110 .
b11110010 -
b1100 /
0,
b101 5
b11101110000 9
b1111001000000101 7
b11101101 C
b1001 D
1(
#240000
0(
#245000
1%
b0 #
b0 B
b0 '
b0 A
0!
b100 5
b1110111000 9
b1111100101110101 7
1,
b11110010 )
b11110010 0
b11110010 ?
b11001110 *
b11001110 1
b11001110 @
b11101101 C
b1001 D
1(
#250000
0(
#255000
0%
b1100001 #
b1100001 B
b1 '
b1 A
1!
b11101000 F
b11000101 E
b11000101 .
b11101000 -
b1101 /
0,
b11 5
b111011100 9
b1111110100101101 7
b11111001 C
b1001 D
1(
#260000
0(
#265000
1%
b0 #
b0 B
b0 '
b0 A
0!
b10 5
b11101110 9
b1111111100001001 7
1,
b11101000 )
b11101000 0
b11101000 ?
b11000101 *
b11000101 1
b11000101 @
b11111001 C
b1001 D
1(
#270000
0(
#275000
0%
b110011 #
b110011 B
b1 '
b1 A
1!
b10111101 F
b1011100 E
b10111101 .
b1011100 -
b1110 /
0,
b1 5
b1110111 9
b1111111111110111 7
b11000101 C
b1001 D
1(
#280000
0(
#285000
1%
b0 #
b0 B
b0 '
b0 A
0!
b1101110 "
b1101110 >
b1 &
b1 <
1$
0:
b0 5
b111011 9
b1 =
b1101110 8
b1101110 7
1,
b10111101 )
b10111101 0
b10111101 ?
b1011100 *
b1011100 1
b1011100 @
b11000101 C
b1001 D
1(
#290000
0(
#295000
16
0%
b11011 #
b11011 B
b1 '
b1 A
1!
0$
b1100101 F
b101101 E
b1100101 .
b101101 -
b1111 /
0,
b10111000000000 9
b10111101 8
b0 =
b0 "
b0 >
b0 &
b0 <
b1000 5
1:
b11100101 C
b1001 D
1(
#300000
0(
#305000
06
1%
b0 #
b0 B
b0 '
b0 A
0!
b111 5
b1011100000000 9
b1101001010111101 7
1,
b1100101 )
b1100101 0
b1100101 ?
b101101 *
b101101 1
b101101 @
b11100101 C
b1001 D
1(
#310000
0(
#315000
0%
b1101110 #
b1101110 B
b1 '
b1 A
1!
b1100011 F
b1010 E
b1010 .
b1100011 -
b10000 /
0,
b110 5
b101110000000 9
b1110100110111101 7
b100011 C
b1001 D
1(
#320000
0(
#325000
1%
b0 #
b0 B
b0 '
b0 A
0!
b101 5
b10111000000 9
b1111010100111101 7
1,
b1100011 )
b1100011 0
b1100011 ?
b1010 *
b1010 1
b1010 @
b100011 C
b1001 D
1(
#330000
0(
#335000
0%
b10001 #
b10001 B
b111 '
b111 A
1!
b10000000 F
b100000 E
b100000 .
b10000000 -
b10001 /
0,
b100 5
b1011100000 9
b1111101011111101 7
b11110010 C
b1001 D
1(
#340000
0(
#345000
1%
b0 #
b0 B
b0 '
b0 A
0!
b11 5
b101110000 9
b1111110111011101 7
1,
b10000000 )
b10000000 0
b10000000 ?
b100000 *
b100000 1
b100000 @
b11110010 C
b1001 D
1(
#350000
0(
#355000
0%
b100100 #
b100100 B
b1 '
b1 A
1!
b10101010 F
b10011101 E
b10011101 .
b10101010 -
b10010 /
0,
b10 5
b10111000 9
b1111111101001101 7
b11101000 C
b1001 D
1(
#360000
0(
#365000
1%
b0 #
b0 B
b0 '
b0 A
0!
b1 5
b1011100 9
b1 =
b101 8
b101 7
1,
b10101010 )
b10101010 0
b10101010 ?
b10011101 *
b10011101 1
b10011101 @
b11101000 C
b1001 D
1(
#370000
0(
#375000
0%
b100011 #
b100011 B
b1 '
b1 A
1!
b101 "
b101 >
b10 &
b10 <
1$
b10010110 F
b10011 E
b10011 .
b10010110 -
b10011 /
0,
0:
b0 5
b101110 9
b10 =
b1111111110101001 7
b101 C
b1001 D
1(
#380000
0(
#385000
16
1%
b0 #
b0 B
b0 '
b0 A
0!
0$
b100110000000 9
b10010110 8
b0 =
b0 "
b0 >
b0 &
b0 <
b1000 5
1:
1,
b10010110 )
b10010110 0
b10010110 ?
b10011 *
b10011 1
b10011 @
b101 C
b1001 D
1(
#390000
0(
#395000
06
0%
b101 #
b101 B
b10 '
b10 A
1!
b1010011 F
b1101 E
b1010011 .
b1101 -
b10100 /
0,
b111 5
b10011000000 9
b1111011100010110 7
b1011 C
b1001 D
1(
#400000
0(
#405000
1%
b0 #
b0 B
b0 '
b0 A
0!
b110 5
b1001100000 9
b1111101111010110 7
1,
b1010011 )
b1010011 0
b1010011 ?
b1101 *
b1101 1
b1101 @
b1011 C
b1001 D
1(
#410000
0(
#415000
0%
b1011 #
b1011 B
b10 '
b10 A
1!
b11010101 F
b1101011 E
b11010101 .
b1101011 -
b10101 /
0,
b101 5
b100110000 9
b1111111000110110 7
b10011 C
b1001 D
1(
#420000
0(
#425000
1%
b0 #
b0 B
b0 '
b0 A
0!
b100 5
b10011000 9
b1111111101100110 7
1,
b11010101 )
b11010101 0
b11010101 ?
b1101011 *
b1101011 1
b1101011 @
b10011 C
b1001 D
1(
#430000
0(
#435000
0%
b1001 #
b1001 B
b1001 '
b1001 A
1!
b10101110 F
b10 E
b10101110 .
b10 -
b10110 /
0,
b11 5
b1001100 9
b1111111111111110 7
b0 C
b1001 D
1(
#440000
0(
#445000
1%
b0 #
b0 B
b0 '
b0 A
0!
b10 5
b100110 9
b1 =
b1001010 8
b1001010 7
1,
b10101110 )
b10101110 0
b10101110 ?
b10 *
b10 1
b10 @
b0 C
b1001 D
1(
#450000
0(
#455000
0%
b100 '
b100 A
1!
b11001111 F
b11101 E
b11001111 .
b11101 -
b10111 /
0,
b1 5
b10011 9
b100100 8
b11 =
b100100 7
b10101010 C
b1001 D
1(
#460000
0(
#465000
1%
b0 '
b0 A
0!
b10001 "
b10001 >
b111 &
b111 <
1$
0:
b0 5
b1001 9
b10001 8
b111 =
b10001 7
1,
b11001111 )
b11001111 0
b11001111 ?
b11101 *
b11101 1
b11101 @
b10101010 C
b1001 D
1(
#470000
0(
#475000
16
0%
b1101 #
b1101 B
b1 '
b1 A
1!
0$
b100011 F
b1010 E
b1010 .
b100011 -
b11000 /
0,
b111010000000 9
b11001111 8
b0 =
b0 "
b0 >
b0 &
b0 <
b1000 5
1:
b100100 C
b1001 D
1(
#480000
0(
#485000
06
1%
b0 #
b0 B
b0 '
b0 A
0!
b111 5
b11101000000 9
b1111001001001111 7
1,
b100011 )
b100011 0
b100011 ?
b1010 *
b1010 1
b1010 @
b100100 C
b1001 D
1(
#490000
0(
#495000
0%
b10001 #
b10001 B
b111 '
b111 A
1!
b11001010 F
b111100 E
b111100 .
b11001010 -
b11001 /
0,
b110 5
b1110100000 9
b1111100110001111 7
b101 C
b1001 D
1(
#500000
0(
#505000
1%
b0 #
b0 B
b0 '
b0 A
0!
b101 5
b111010000 9
b1111110100101111 7
1,
b11001010 )
b11001010 0
b11001010 ?
b111100 *
b111100 1
b111100 @
b101 C
b1001 D
1(
#510000
0(
#515000
0%
b101 #
b101 B
b110 '
b110 A
1!
b11110010 F
b10001010 E
b10001010 .
b11110010 -
b11010 /
0,
b100 5
b11101000 9
b1111111011111111 7
b11010101 C
b1001 D
1(
#520000
0(
#525000
1%
b0 #
b0 B
b0 '
b0 A
0!
b11 5
b1110100 9
b1111111111100111 7
1,
b11110010 )
b11110010 0
b11110010 ?
b10001010 *
b10001010 1
b10001010 @
b11010101 C
b1001 D
1(
#530000
0(
#535000
0%
b1101010 #
b1101010 B
b1 '
b1 A
1!
b11011000 F
b1000001 E
b11011000 .
b1000001 -
b11011 /
0,
b10 5
b111010 9
b1 =
b1011011 8
b1011011 7
b10 C
b1001 D
1(
#540000
0(
#545000
1%
b0 #
b0 B
b0 '
b0 A
0!
b1 5
b11101 9
b100001 8
b11 =
b100001 7
1,
b11011000 )
b11011000 0
b11011000 ?
b1000001 *
b1000001 1
b1000001 @
b10 C
b1001 D
1(
#550000
0(
#555000
0%
b1010111 '
b1010111 A
1!
b100 "
b100 >
b111 &
b111 <
1$
b10001001 F
b1111000 E
b10001001 .
b1111000 -
b11100 /
0,
0:
b0 5
b1110 9
b100 8
b111 =
b100 7
b100001 C
b1001 D
1(
#560000
0(
#565000
16
1%
b0 '
b0 A
0!
0$
b11110000000000 9
b10001001 8
b0 =
b0 "
b0 >
b0 &
b0 <
b1000 5
1:
1,
b10001001 )
b10001001 0
b10001001 ?
b1111000 *
b1111000 1
b1111000 @
b100001 C
b1001 D
1(
#570000
0(
#575000
06
0%
b100 #
b100 B
b111 '
b111 A
1!
b11101011 F
b10110110 E
b10110110 .
b11101011 -
b11101 /
0,
b111 5
b1111000000000 9
b1100010010001001 7
b1111 C
b1001 D
1(
#580000
0(
#585000
1%
b0 #
b0 B
b0 '
b0 A
0!
b110 5
b111100000000 9
b1110001010001001 7
1,
b11101011 )
b11101011 0
b11101011 ?
b10110110 *
b10110110 1
b10110110 @
b1111 C
b1001 D
1(
#590000
0(
#595000
0%
b101 #
b101 B
b11 '
b11 A
1!
b11000110 F
b10101110 E
b10101110 .
b11000110 -
b11110 /
0,
b101 5
b11110000000 9
b1111000110001001 7
b1010010 C
b1001 D
1(
#600000
0(
#605000
1%
b0 #
b0 B
b0 '
b0 A
0!
b100 5
b1111000000 9
b1111100100001001 7
1,
b11000110 )
b11000110 0
b11000110 ?
b10101110 *
b10101110 1
b10101110 @
b1010010 C
b1001 D
1(
#610000
0(
#615000
0%
b10110 #
b10110 B
b11 '
b11 A
1!
b10111100 F
b101010 E
b101010 .
b10111100 -
b11111 /
0,
b11 5
b111100000 9
b1111110011001001 7
b11110010 C
b1001 D
1(
#620000
0(
#625000
1%
b0 #
b0 B
b0 '
b0 A
0!
b10 5
b11110000 9
b1111111010101001 7
1,
b10111100 )
b10111100 0
b10111100 ?
b101010 *
b101010 1
b101010 @
b11110010 C
b1001 D
1(
#630000
0(
#635000
0%
b1101000 #
b1101000 B
b1 '
b1 A
1!
b1110001 F
b1011 E
b1110001 .
b1011 -
b100000 /
0,
b1 5
b1111000 9
b1111111110011001 7
b1010110 C
b1001 D
1(
#640000
0(
#645000
1%
b0 #
b0 B
b0 '
b0 A
0!
b10001 "
b10001 >
b1 &
b1 <
1$
0:
b0 5
b111100 9
b1 =
b10001 8
b10001 7
1,
b1110001 )
b1110001 0
b1110001 ?
b1011 *
b1011 1
b1011 @
b1010110 C
b1001 D
1(
#650000
0(
#655000
16
0%
b10101 #
b10101 B
b11 '
b11 A
1!
0$
b10000101 F
b1001111 E
b1001111 .
b10000101 -
b100001 /
0,
b10110000000 9
b1110001 8
b0 =
b0 "
b0 >
b0 &
b0 <
b1000 5
1:
b10001001 C
b1001 D
1(
#660000
0(
#665000
06
1%
b0 #
b0 B
b0 '
b0 A
0!
b111 5
b1011000000 9
b1111101011110001 7
1,
b10000101 )
b10000101 0
b10000101 ?
b1001111 *
b1001111 1
b1001111 @
b10001001 C
b1001 D
1(
#670000
0(
#675000
0%
b10001 #
b10001 B
b1 '
b1 A
1!
b111011 F
b111010 E
b111010 .
b111011 -
b100010 /
0,
b110 5
b101100000 9
b1111110110110001 7
b11101011 C
b1001 D
1(
#680000
0(
#685000
1%
b0 #
b0 B
b0 '
b0 A
0!
b101 5
b10110000 9
b1111111100010001 7
1,
b111011 )
b111011 0
b111011 ?
b111010 *
b111010 1
b111010 @
b11101011 C
b1001 D
1(
#690000
0(
#695000
0%
b110101 #
b110101 B
b1 '
b1 A
1!
b1111110 F
b10101 E
b10101 .
b1111110 -
b100011 /
0,
b100 5
b1011000 9
b1111111111000001 7
b11000110 C
b1001 D
1(
#700000
0(
#705000
1%
b0 #
b0 B
b0 '
b0 A
0!
b11 5
b101100 9
b1 =
b11001 8
b11001 7
1,
b1111110 )
b1111110 0
b1111110 ?
b10101 *
b10101 1
b10101 @
b11000110 C
b1001 D
1(
#710000
0(
#715000
0%
b11000 #
b11000 B
b1 '
b1 A
1!
b11110001 F
b11011001 E
b11011001 .
b11110001 -
b100100 /
0,
b10 5
b10110 9
b10 =
b1111111111101101 7
b10100 C
b1001 D
1(
#720000
0(
#725000
1%
b0 #
b0 B
b0 '
b0 A
0!
b1 5
b1011 9
b11 8
b101 =
b11 7
1,
b11110001 )
b11110001 0
b11110001 ?
b11011001 *
b11011001 1
b11011001 @
b10100 C
b1001 D
1(
#730000
0(
#735000
0%
b10100 #
b10100 B
b100 '
b100 A
1!
b11 "
b11 >
b1010 &
b1010 <
1$
b1100010 F
b1001100 E
b1001100 .
b1100010 -
b100101 /
0,
0:
b0 5
b101 9
b1010 =
b1111111111111000 7
b11 C
b1001 D
1(
#740000
0(
#745000
16
1%
b0 #
b0 B
b0 '
b0 A
0!
0$
b10011000000000 9
b1100010 8
b0 =
b0 "
b0 >
b0 &
b0 <
b1000 5
1:
1,
b1100010 )
b1100010 0
b1100010 ?
b1001100 *
b1001100 1
b1001100 @
b11 C
b1001 D
1(
#750000
0(
#755000
06
0%
b11 #
b11 B
b1010 '
b1010 A
1!
b10011111 F
b10001111 E
b10001111 .
b10011111 -
b100110 /
0,
b111 5
b1001100000000 9
b1101101001100010 7
b10000101 C
b1001 D
1(
#760000
0(
#765000
1%
b0 #
b0 B
b0 '
b0 A
0!
b110 5
b100110000000 9
b1110110101100010 7
1,
b10011111 )
b10011111 0
b10011111 ?
b10001111 *
b10001111 1
b10001111 @
b10000101 C
b1001 D
1(
#770000
0(
#775000
0%
b110110 #
b110110 B
b1 '
b1 A
1!
b11111000 F
b10110111 E
b10110111 .
b11111000 -
b100111 /
0,
b101 5
b10011000000 9
b1111011011100010 7
b111011 C
b1001 D
1(
#780000
0(
#785000
1%
b0 #
b0 B
b0 '
b0 A
0!
b100 5
b1001100000 9
b1111101110100010 7
1,
b11111000 )
b11111000 0
b11111000 ?
b10110111 *
b10110111 1
b10110111 @
b111011 C
b1001 D
1(
#790000
0(
#795000
0%
b1 #
b1 B
b1 '
b1 A
1!
b10011111 F
b1011100 E
b1011100 .
b10011111 -
b101000 /
0,
b11 5
b100110000 9
b1111111000000010 7
b0 C
b1001 D
1(
#800000
0(
#805000
1%
b0 #
b0 B
b0 '
b0 A
0!
b10 5
b10011000 9
b1111111100110010 7
1,
b10011111 )
b10011111 0
b10011111 ?
b1011100 *
b1011100 1
b1011100 @
b0 C
b1001 D
1(
#810000
0(
#815000
0%
b110 '
b110 A
1!
b10001001 F
b1011011 E
b10001001 .
b1011011 -
b101001 /
0,
b1 5
b1001100 9
b1111111111001010 7
b11110001 C
b1001 D
1(
#820000
0(
#825000
1%
b0 '
b0 A
0!
b10110 "
b10110 >
b1 &
b1 <
1$
0:
b0 5
b100110 9
b1 =
b10110 8
b10110 7
1,
b10001001 )
b10001001 0
b10001001 ?
b1011011 *
b1011011 1
b1011011 @
b11110001 C
b1001 D
1(
#830000
0(
#835000
16
0%
b11000 #
b11000 B
b1 '
b1 A
1!
0$
b11010000 F
b1001001 E
b11010000 .
b1001001 -
b101010 /
0,
b10110110000000 9
b10001001 8
b0 =
b0 "
b0 >
b0 &
b0 <
b1000 5
1:
b1100010 C
b1001 D
1(
#840000
0(
#845000
06
1%
b0 #
b0 B
b0 '
b0 A
0!
b111 5
b1011011000000 9
b1101001100001001 7
1,
b11010000 )
b11010000 0
b11010000 ?
b1001001 *
b1001001 1
b1001001 @
b1100010 C
b1001 D
1(
#850000
0(
#855000
0%
b10110 #
b10110 B
b1 '
b1 A
1!
b11010111 F
b1010001 E
b1010001 .
b11010111 -
b101011 /
0,
b110 5
b101101100000 9
b1110100111001001 7
b10011111 C
b1001 D
1(
#860000
0(
#865000
1%
b0 #
b0 B
b0 '
b0 A
0!
b101 5
b10110110000 9
b1111010100101001 7
1,
b11010111 )
b11010111 0
b11010111 ?
b1010001 *
b1010001 1
b1010001 @
b10011111 C
b1001 D
1(
#870000
0(
